distgfs.py
distgfs-1.2.0.dist-info/METADATA
distgfs-1.2.0.dist-info/WHEEL
distgfs-1.2.0.dist-info/licenses/LICENSE
distgfs-1.2.0.dist-info/RECORD
