Metadata-Version: 2.4
Name: distgfs
Version: 1.2.0
Summary: Distributed global function search via dlib
Author-email: Ivan Raikov <ivan.g.raikov@gmail.com>
License: GPL-3.0-or-later
License-File: LICENSE
Keywords: GFS,MPI,distributed computing,distributed optimization,mpi4py,optimization
Requires-Python: >=3.9
Requires-Dist: distwq>=1.1.0
Requires-Dist: dlib>=19.24.0
Requires-Dist: h5py>=3.7.0
Requires-Dist: mpi4py>=4.0.0
Requires-Dist: numpy>=1.26.2
Requires-Dist: ruff>=0.6.9
